{
  "id": 1309,
  "key": "robin",
  "name": "知更鸟",
  "abbr": "知更鸟",
  "star": 5,
  "elem": "物理",
  "allegiance": "null",
  "weapon": "同谐",
  "sp": 102,
  "desc": "出生于匹诺康尼，闻名银河的天环族歌者，举止从容优雅的少女。此次受家族宴请回到故乡，在「谐乐大典」为众宾献歌一曲。可以依靠「同谐」的力量传递歌声，在歌迷乃至万界生灵之中展现「共鸣」。",
  "cncv": "null",
  "jpcv": "null",
  "baseAttr": {
    "atk": 640.33,
    "hp": 1281,
    "def": 485.1,
    "speed": 102,
    "cpct": 5,
    "cdmg": 50,
    "aggro": 160
  },
  "growAttr": {
    "atk": 4.356,
    "hp": 8.737,
    "def": 3.3,
    "speed": 0
  },
  "talentId": {
    "130930": "q",
    "130920": "e",
    "130910": "a",
    "130950": "z",
    "130940": "t"
  },
  "talentCons": {
    "3": "e",
    "5": "a",
    "a": 5,
    "e": 3,
    "q": 3,
    "t": 5
  },
  "talent": {
    "a": {
      "id": 130910,
      "name": "扑翼白声",
      "type": "普攻",
      "tag": "单攻",
      "desc": "对指定敌方单体造成等同于知更鸟<nobr>$1[i]%</nobr>攻击力的<span>物理</span>属性伤害。",
      "tables": {
        "1": {
          "name": "技能伤害",
          "isSame": false,
          "values": [
            0.5,
            0.6,
            0.7,
            0.8,
            0.9,
            1,
            1.1,
            1.2,
            1.3
          ]
        }
      }
    },
    "e": {
      "id": 130920,
      "name": "翎之咏叹调",
      "type": "战技",
      "tag": "辅助",
      "desc": "使我方全体造成的伤害提高<nobr>$1[i]%</nobr>，持续<nobr>3</nobr>回合，知更鸟每回合开始时持续回合数减1。",
      "tables": {
        "1": {
          "name": "伤害提高",
          "isSame": false,
          "values": [
            0.25,
            0.275,
            0.3,
            0.325,
            0.35,
            0.375,
            0.4063,
            0.4375,
            0.4688,
            0.5,
            0.525,
            0.55,
            0.575,
            0.6,
            0.625
          ]
        }
      }
    },
    "q": {
      "id": 130930,
      "name": "千音迭奏，群星赋格",
      "type": "终结技",
      "tag": "辅助",
      "desc": "知更鸟进入【协奏】状态，使我方全体攻击力提高，提高数值等同于知更鸟攻击力的<nobr>$1[i]%</nobr>+<nobr>$2[i]</nobr>点，且使除自身以外的队友立即行动。我方目标每次施放攻击后，知更鸟会额外造成1次等同于其自身<nobr>$3[i]%</nobr>攻击力的物理属性<u>附加伤害</u>，该伤害暴击率固定为<nobr>100%</nobr>，暴击伤害固定为<nobr>150%</nobr>。<br />处于【协奏】状态时，知更鸟免疫<u>控制类负面状态</u>，在【协奏】状态结束前不会进入自己回合且无法行动。<br />行动序列上出现【协奏】倒计时，倒计时回合开始时知更鸟退出【协奏】状态并立即行动，倒计时固定拥有<nobr>90</nobr>点速度。",
      "tables": {
        "1": {
          "name": "攻击力提升·百分比",
          "isSame": false,
          "values": [
            0.152,
            0.1596,
            0.1672,
            0.1748,
            0.1824,
            0.19,
            0.1995,
            0.209,
            0.2185,
            0.228,
            0.2356,
            0.2432,
            0.2508,
            0.2584,
            0.266
          ]
        },
        "2": {
          "name": "攻击力提升·固定值",
          "isSame": false,
          "values": [
            50,
            65,
            80,
            95,
            110,
            125,
            144,
            163,
            181,
            200,
            215,
            230,
            245,
            260,
            275
          ]
        },
        "3": {
          "name": "附加伤害",
          "isSame": false,
          "values": [
            0.72,
            0.768,
            0.816,
            0.864,
            0.912,
            0.96,
            1.02,
            1.08,
            1.04,
            1.2,
            1.248,
            1.296,
            1.344,
            1.392,
            1.44
          ]
        }
      }
    },
    "t": {
      "id": 130940,
      "name": "调性合颂",
      "type": "天赋",
      "tag": "妨害",
      "desc": "使我方全体暴击伤害提高<nobr>$1[i]%</nobr>，且我方目标攻击敌方目标后，知更鸟额外为自身恢复<nobr>2</nobr>点能量。",
      "tables": {
        "1": {
          "name": "能量恢复",
          "isSame": false,
          "values": [
            0.05,
            0.065,
            0.08,
            0.095,
            0.11,
            0.125,
            0.1438,
            0.1625,
            0.1813,
            0.2,
            0.215,
            0.23,
            0.245,
            0.26,
            0.275
          ]
        }
      }
    },
    "z": {
      "id": 130950,
      "name": "酣醉序曲",
      "type": "秘技",
      "tag": "辅助",
      "desc": "施放秘技后，在自身周围展开持续<nobr>15</nobr>秒的特殊领域，处于领域内的敌人不会对知更鸟发动攻击，且在领域展开期间跟随知更鸟。领域展开期间进入战斗后，每个波次开始时知更鸟额外恢复<nobr>5</nobr>点能量。我方制造的领域效果最多存在1个。",
      "tables": {}
    }
  },
  "cons": {
    "1": {
      "name": "微笑的国度",
      "desc": "知更鸟处于【协奏】状态时，我方目标施放普攻、战技、终结技时获得1层【装饰音】，持有【装饰音】的目标速度提高<nobr>15%</nobr>，最多叠加<nobr>2</nobr>层，且攻击后知更鸟额外造成的物理属性附加伤害倍率提高<nobr>72%</nobr>。"
    },
    "2": {
      "name": "两者的午茶",
      "desc": "天赋的暴击伤害提高效果额外提高<nobr>20%</nobr>，能量恢复效果额外提高<nobr>1</nobr>点。"
    },
    "3": {
      "name": "倒悬的弦宫",
      "desc": "战技等级+2，最多不超过<nobr>15</nobr>级，终结技等级+2，最多不超过<nobr>15</nobr>级。"
    },
    "4": {
      "name": "雨滴的钥匙",
      "desc": "施放终结技时，解除我方全体的控制类负面状态，使我方全体在知更鸟处于【协奏】状态期间的效果抵抗提高<nobr>50%</nobr>。"
    },
    "5": {
      "name": "孤星的眼泪",
      "desc": "普攻等级+1，最多不超过<nobr>10</nobr>级，天赋等级+2，最多不超过<nobr>15</nobr>级。"
    },
    "6": {
      "name": "月隐的午夜",
      "desc": "知更鸟处于【协奏】状态时，我方全体全属性抗性穿透提高<nobr>20%</nobr>，且触发的前<nobr>6</nobr>次附加伤害的暴击伤害提高<nobr>200%</nobr>。施放终结技后重置触发次数。"
    }
  },
  "attr": {
    "0": {
      "promote": 0,
      "maxLevel": 20,
      "cost": {
        "29328": 3200,
        "549437": 4
      },
      "grow": {
        "atk": 4.356,
        "hp": 8.737,
        "def": 3.3,
        "speed": 0
      },
      "attrs": {
        "atk": 87.12,
        "hp": 174,
        "def": 66,
        "speed": 102,
        "cpct": 5,
        "cdmg": 50,
        "aggro": 160
      }
    },
    "1": {
      "promote": 1,
      "maxLevel": 30,
      "cost": {
        "29328": 6400,
        "549437": 8
      },
      "grow": {
        "atk": 4.356,
        "hp": 8.737,
        "def": 3.3,
        "speed": 0
      },
      "attrs": {
        "atk": 121.968,
        "hp": 244.636,
        "def": 92.4,
        "speed": 102,
        "cpct": 5,
        "cdmg": 50,
        "aggro": 160
      }
    },
    "2": {
      "promote": 2,
      "maxLevel": 40,
      "cost": {
        "29328": 12000,
        "633378": 5,
        "983280": 4
      },
      "grow": {
        "atk": 4.356,
        "hp": 8.737,
        "def": 3.3,
        "speed": 0
      },
      "attrs": {
        "atk": 156.816,
        "hp": 314.532,
        "def": 118.8,
        "speed": 102,
        "cpct": 5,
        "cdmg": 50,
        "aggro": 160
      }
    },
    "3": {
      "promote": 3,
      "maxLevel": 50,
      "cost": {
        "29328": 32,
        "633378": 8,
        "983280": 6
      },
      "grow": {
        "atk": 4.356,
        "hp": 8.737,
        "def": 3.3,
        "speed": 0
      },
      "attrs": {
        "atk": 191.664,
        "hp": 384.428,
        "def": 145.2,
        "speed": 102,
        "cpct": 5,
        "cdmg": 50,
        "aggro": 160
      }
    },
    "4": {
      "promote": 4,
      "maxLevel": 60,
      "cost": {
        "29328": 64000,
        "717319": 5,
        "983280": 8
      },
      "grow": {
        "atk": 4.356,
        "hp": 8.737,
        "def": 3.3,
        "speed": 0
      },
      "attrs": {
        "atk": 226.512,
        "hp": 454.324,
        "def": 171.6,
        "speed": 102,
        "cpct": 5,
        "cdmg": 50,
        "aggro": 160
      }
    },
    "5": {
      "promote": 5,
      "maxLevel": 70,
      "cost": {
        "29328": 128000,
        "717319": 7,
        "983280": 10
      },
      "grow": {
        "atk": 4.356,
        "hp": 8.737,
        "def": 3.3,
        "speed": 0
      },
      "attrs": {
        "atk": 261.36,
        "hp": 524.22,
        "def": 198,
        "speed": 102,
        "cpct": 5,
        "cdmg": 50,
        "aggro": 160
      }
    },
    "6": {
      "promote": 6,
      "maxLevel": 80,
      "cost": {},
      "grow": {
        "atk": 4.356,
        "hp": 8.737,
        "def": 3.3,
        "speed": 0
      },
      "attrs": {
        "atk": 296.208,
        "hp": 594.116,
        "def": 224.4,
        "speed": 102,
        "cpct": 5,
        "cdmg": 50,
        "aggro": 160
      }
    }
  },
  "tree": {
    "1309201": {
      "key": "atk",
      "value": 4.00000000372529
    },
    "1309202": {
      "key": "hp",
      "value": 4.00000000372529
    },
    "1309203": {
      "key": "atk",
      "value": 4.00000000372529
    },
    "1309204": {
      "key": "speed",
      "value": 2
    },
    "1309205": {
      "key": "atk",
      "value": 6.0000000055879354
    },
    "1309206": {
      "key": "hp",
      "value": 6.0000000055879354
    },
    "1309207": {
      "key": "atk",
      "value": 6.0000000055879354
    },
    "1309208": {
      "key": "speed",
      "value": 3
    },
    "1309209": {
      "key": "hp",
      "value": 8.00000000745058
    },
    "1309210": {
      "key": "atk",
      "value": 8.00000000745058
    }
  },
  "treeData": {
    "130901": {
      "id": 130901,
      "type": "skill",
      "root": true,
      "name": "华彩花腔",
      "levelReq": 0,
      "desc": "战斗开始时，自身行动提前<nobr>25%</nobr>",
      "cost": {},
      "idx": 1,
      "children": []
    },
    "130903": {
      "id": 130903,
      "type": "skill",
      "root": true,
      "name": "模进乐段",
      "levelReq": 0,
      "desc": "若自身当前生命值百分比小于等于<nobr>50%</nobr>，触发天赋时额外回复等同于自身生命上限<nobr>2%</nobr>的生命值。",
      "cost": {},
      "idx": 3,
      "children": []
    },
    "130902": {
      "id": 130902,
      "type": "skill",
      "root": true,
      "name": "即兴装饰",
      "levelReq": 0,
      "desc": "处于【协奏】状态时，我方全体发动追加攻击造成的暴击伤害提高<nobr>10%</nobr>。",
      "cost": {},
      "idx": 2,
      "children": []
    }
  }
}